cfrainbow/__init__.py
cfrainbow/cfr/__init__.py
cfrainbow/cfr/cfr_base.py
cfrainbow/cfr/cfr_br.py
cfrainbow/cfr/cfr_discounted.py
cfrainbow/cfr/cfr_exp.py
cfrainbow/cfr/cfr_internal.py
cfrainbow/cfr/cfr_joint_reconstruction.py
cfrainbow/cfr/cfr_lazy.py
cfrainbow/cfr/cfr_monte_carlo_chance_sampling.py
cfrainbow/cfr/cfr_monte_carlo_external_sampling.py
cfrainbow/cfr/cfr_monte_carlo_outcome_sampling.py
cfrainbow/cfr/cfr_predictive_plus.py
cfrainbow/cfr/cfr_pure.py
cfrainbow/cfr/cfr_sampling.py
cfrainbow/cfr/cfr_vanilla.py
cfrainbow/games/__init__.py
cfrainbow/games/custom_efg.py
cfrainbow/main.py
cfrainbow/rm/__init__.py
cfrainbow/rm/external.py
cfrainbow/rm/internal.py
cfrainbow/rm/unbound.py
cfrainbow/spiel_types.py
cfrainbow/strategy/__init__.py
cfrainbow/strategy/equilibria.py
cfrainbow/strategy/space.py
cfrainbow/utils.py
cfrainbow-0.1.1.dist-info/LICENSE.md
cfrainbow-0.1.1.dist-info/METADATA
cfrainbow-0.1.1.dist-info/WHEEL
cfrainbow-0.1.1.dist-info/RECORD
